Metadata-Version: 2.1
Name: brainfoodstyle
Version: 0.1
Summary: Librería de estilo plots Brain Food
Home-page: UNKNOWN
Author: J. Ignacio del Rio
Author-email: jorge.delrio@ug.uchile.cl
License: MIT
Keywords: brainfood,style,plot
Platform: UNKNOWN
